pav_logger/__init__.py
pav_logger/pav_logger.py
pav_logger/utils.py
pav_logger-1.0.1.dist-info/LICENSE.txt
pav_logger-1.0.1.dist-info/METADATA
pav_logger-1.0.1.dist-info/WHEEL
pav_logger-1.0.1.dist-info/top_level.txt
pav_logger-1.0.1.dist-info/RECORD
