Metadata-Version: 2.1
Name: pav-logger
Version: 1.0.1
Summary: PavLogger provides the ability to log debug and exception to a text file or a SQLite database with optional Backtrace output.
Home-page: https://github.com/PavtheDog/pav_logger
Author: PavtheDog
Author-email: 
License: UNKNOWN
Platform: UNKNOWN
Classifier: Programming Language :: Python :: 3
Classifier: Programming Language :: Python :: 3.6
Classifier: Programming Language :: Python :: 3.7
Classifier: License :: OSI Approved :: MIT License
Classifier: Operating System :: OS Independent
Provides-Extra: dev
Requires-Dist: pytest (>=3.7) ; extra == 'dev'
